setup.py
parsnip/__init__.py
parsnip/serialize.py
parsnip/stardestroyer.py
parsnip.egg-info/PKG-INFO
parsnip.egg-info/SOURCES.txt
parsnip.egg-info/dependency_links.txt
parsnip.egg-info/top_level.txt