Metadata-Version: 1.1
Name: parsnip
Version: 0.1.0
Summary: Library for parsing and manipulating Python code
Home-page: https://github.com/kentfrazier/parsnip
Author: Kent Frazier
Author-email: kentfrazier@gmail.com
License: UNKNOWN
Platform: UNKNOWN
Classifier: Development Status :: 3 - Alpha
Classifier: Intended Audience :: Developers
Classifier: License :: OSI Approved :: Apache Software License
Classifier: Operating System :: OS Independent
Classifier: Programming Language :: Python :: 2.7
Classifier: Programming Language :: Python :: Implementation :: CPython
